{"version":1,"resource":"file:///home/vollpe/.config/quickshell/modules/PopupTest.qml","entries":[{"id":"jSLa.qml","timestamp":1778169406772},{"id":"zenQ.qml","timestamp":1778169428847},{"id":"Scqp.qml","timestamp":1778169466481},{"id":"lxfJ.qml","timestamp":1778169501899},{"id":"VOHK.qml","timestamp":1778169629963},{"id":"uwNq.qml","timestamp":1778169985338},{"id":"9ecy.qml","timestamp":1778170000660},{"id":"KnXj.qml","timestamp":1778170137076},{"id":"9o08.qml","timestamp":1778170152864},{"id":"Jiuu.qml","timestamp":1778170168058}]}