{"version":1,"resource":"file:///home/vollpe/.config/quickshell/widgets/Slider.qml","entries":[{"id":"d68I.qml","timestamp":1777817910556},{"id":"FdgT.qml","source":"renamed.source","sourceDescription":"~/.config/quickshell/widgets/slider.qml","timestamp":1777818082697},{"id":"5Oaz.qml","timestamp":1777818186556},{"id":"J6Uz.qml","timestamp":1777818230488},{"id":"ca1X.qml","timestamp":1777819009705},{"id":"bn43.qml","timestamp":1777819060452},{"id":"EMAm.qml","timestamp":1777819153264},{"id":"GmBA.qml","timestamp":1777819184080},{"id":"aZLe.qml","timestamp":1777819213377},{"id":"ZaGt.qml","timestamp":1777819466442},{"id":"uzPi.qml","timestamp":1777819533513},{"id":"fOP6.qml","timestamp":1777819586068},{"id":"8xTI.qml","timestamp":1777819673558},{"id":"NebL.qml","timestamp":1777819703768},{"id":"rZJW.qml","timestamp":1777819751054},{"id":"jFsa.qml","timestamp":1777819776192},{"id":"yYyz.qml","timestamp":1777820054849},{"id":"JelB.qml","timestamp":1777820217651},{"id":"0ntD.qml","timestamp":1777820232860},{"id":"IEvR.qml","timestamp":1777820456693},{"id":"6DYy.qml","timestamp":1777820507348},{"id":"DJYd.qml","timestamp":1777820577696},{"id":"q6m5.qml","source":"undoRedo.source","timestamp":1777820581971},{"id":"WWa2.qml","timestamp":1777820672074},{"id":"r9tg.qml","timestamp":1777820895176},{"id":"qrA9.qml","timestamp":1777821114739},{"id":"5AKN.qml","timestamp":1777821376705},{"id":"gqZO.qml","timestamp":1777821443648},{"id":"DSfI.qml","timestamp":1777839833095},{"id":"YFAG.qml","timestamp":1777840640365},{"id":"OsFy.qml","timestamp":1777840743346},{"id":"1ncR.qml","timestamp":1777840787746},{"id":"YGBA.qml","timestamp":1777840900060},{"id":"MTlT.qml","timestamp":1777920748876},{"id":"gSY2.qml","timestamp":1777988918718},{"id":"MFQL.qml","timestamp":1777988934029},{"id":"FrOk.qml","timestamp":1777988963506},{"id":"gnOu.qml","timestamp":1777989038669},{"id":"ik8a.qml","timestamp":1777989804414},{"id":"WiXY.qml","timestamp":1777989970076},{"id":"BfRO.qml","timestamp":1777989998566},{"id":"tYBH.qml","timestamp":1777990151264},{"id":"PTPL.qml","timestamp":1777990498772},{"id":"cgaN.qml","timestamp":1777990635292},{"id":"IVTM.qml","timestamp":1777990682936},{"id":"4fWj.qml","timestamp":1778012111020},{"id":"zuKd.qml","timestamp":1778012236087}]}