{"version":1,"resource":"file:///home/vollpe/.config/quickshell/services/SysInfo.qml","entries":[{"id":"s95x.qml","timestamp":1777822990954},{"id":"KY69.qml","timestamp":1777824316217},{"id":"ohOz.qml","timestamp":1777824344327},{"id":"RIsO.qml","timestamp":1777825352580},{"id":"gu2e.qml","timestamp":1777826179300},{"id":"WDCr.qml","timestamp":1777826400303},{"id":"FyRz.qml","timestamp":1777826430765},{"id":"Qpkc.qml","timestamp":1777827015939},{"id":"acXp.qml","timestamp":1778012385362},{"id":"1Bug.qml","timestamp":1778012435622}]}