{"version":1,"resource":"file:///home/vollpe/Downloads/olicyber/not_morse_code.py","entries":[{"id":"7E2R.py","timestamp":1773743630020},{"id":"SbeI.py","timestamp":1773743640493},{"id":"9Dmx.py","timestamp":1773743723963},{"id":"EbAo.py","timestamp":1773743734904},{"id":"5E7G.py","timestamp":1773743811279},{"id":"YZri.py","timestamp":1773743836012},{"id":"nP2R.py","timestamp":1773743901792},{"id":"N9O5.py","timestamp":1773744445797},{"id":"6miZ.py","timestamp":1773744472595},{"id":"rkhZ.py","timestamp":1773744521703},{"id":"zDli.py","timestamp":1773744603440},{"id":"9hcw.py","timestamp":1773744619500},{"id":"yuL8.py","timestamp":1773744691462},{"id":"I0pZ.py","timestamp":1773744737394},{"id":"P9OJ.py","timestamp":1773744753627},{"id":"tmdf.py","timestamp":1773744774060},{"id":"WSLC.py","timestamp":1773744964072},{"id":"NSiO.py","timestamp":1773744984670},{"id":"Fg3g.py","timestamp":1773745011115},{"id":"Lr81.py","timestamp":1773745105813},{"id":"wub7.py","timestamp":1773745119392},{"id":"PmPT.py","timestamp":1773745129534},{"id":"yzay.py","timestamp":1773745153661},{"id":"TnvI.py","timestamp":1773745172027},{"id":"HL5Q.py","timestamp":1773745341295},{"id":"9hhy.py","timestamp":1773745397787}]}